negentropior/__init__.py
negentropior/algorithm/__init__.py
negentropior/algorithm/aftertreat/__init__.py
negentropior/algorithm/pretreat/__init__.py
negentropior/tools/__init__.py
negentropior/tools/datatype.py
negentropior/tools/time.py
negentropior/tools/Office/__init__.py
negentropior/tools/Office/excel.py
negentropior/tools/Office/ppt.py
negentropior/tools/Office/word.py
negentropior/tools/Web/__init__.py
negentropior/tools/Web/flaskAPI.py
negentropior/tools/alarm/__init__.py
negentropior/tools/alarm/ding.py
negentropior/tools/alarm/email.py
negentropior/tools/alarm/fly.py
negentropior/tools/connect/AliyunOss.py
negentropior/tools/connect/Influxdb.py
negentropior/tools/connect/Mysql.py
negentropior/tools/connect/Rabbitmq.py
negentropior/tools/connect/Redis.py
negentropior/tools/connect/Tdengine.py
negentropior/tools/connect/__init__.py
negentropior/tools/log/__init__.py
negentropior/tools/log/timeroatingfilehandler.py
negentropior/tools/program/__init__.py
negentropior/tools/program/template_ilab1.py
negentropior/tools/program/templates.py
negentropior-0.1.5.dist-info/LICENSE
negentropior-0.1.5.dist-info/METADATA
negentropior-0.1.5.dist-info/WHEEL
negentropior-0.1.5.dist-info/top_level.txt
negentropior-0.1.5.dist-info/RECORD
