Metadata-Version: 2.1
Name: negentropior
Version: 0.1.5
Summary: ILabor algorithm group tools 算法组常用工具方法
Author: Yi OuYang, ZhiWen Wang
Author-email: yiouyang143@gmail.com
Classifier: Programming Language :: Python :: 3
Classifier: License :: OSI Approved :: MIT License
Classifier: Operating System :: OS Independent
License-File: LICENSE
